zi_api_auth_client/__init__.py
zi_api_auth_client/zi_api_auth_client.py
zi_api_auth_client-2.0.3.dist-info/licenses/LICENSE.txt
zi_api_auth_client-2.0.3.dist-info/METADATA
zi_api_auth_client-2.0.3.dist-info/WHEEL
zi_api_auth_client-2.0.3.dist-info/top_level.txt
zi_api_auth_client-2.0.3.dist-info/RECORD
