Metadata-Version: 2.4
Name: zi_api_auth_client
Version: 2.0.3
Summary: A library that supports username-password and PKI authentication methods for enterprise-api
Home-page: https://github.com/Zoominfo/api-auth-python-client
Author: Krishna Teja Dinavahi
Author-email: krishnateja.dinavahi@zoominfo.com
License: MIT
Keywords: ZoomInfo enterprise-api pki-auth
Classifier: License :: OSI Approved :: MIT License
Classifier: Programming Language :: Python :: 3
License-File: LICENSE.txt
Requires-Dist: PyJWT<3.0.0,>=2.6.0
Requires-Dist: requests<3.0.0,>=2.32.4
Requires-Dist: cryptography>=41.0.6
Dynamic: author
Dynamic: author-email
Dynamic: classifier
Dynamic: description
Dynamic: home-page
Dynamic: keywords
Dynamic: license
Dynamic: license-file
Dynamic: requires-dist
Dynamic: summary
